vdataset/__init__.py
vdataset/__main__.py
vdataset/_cmd.py
vdataset/_core.py
vdataset/_mount_samples.py
virtual_dataset-1.0.1.dist-info/LICENCE.txt
virtual_dataset-1.0.1.dist-info/METADATA
virtual_dataset-1.0.1.dist-info/WHEEL
virtual_dataset-1.0.1.dist-info/entry_points.txt
virtual_dataset-1.0.1.dist-info/top_level.txt
virtual_dataset-1.0.1.dist-info/RECORD
