Metadata-Version: 2.1
Name: virtual-dataset
Version: 1.0.1
Summary: A small utility that allows to mount virtually a list of files as a folder.
Home-page: https://github.com/nhamilakis/virtual-dataset
Author: Nicolas Hamilakis
Maintainer: Nicolas Hamilakis
Maintainer-email: nick.hamilakis562@gmail.com
License: MIT
Project-URL: Github, https://github.com/nhamilakis/virtual-dataset
Project-URL: Pip, https://pypi.org/project/virtual-dataset
Keywords: todo
Platform: any
Classifier: Development Status :: 3 - Alpha
Classifier: License :: OSI Approved :: GNU General Public License v3 (GPLv3)
Classifier: Operating System :: POSIX :: Linux
Classifier: Programming Language :: Python
Classifier: Programming Language :: Python :: 3
